{"status":"done","publicPath":"/templates/bundle/","chunks":{"404":[{"name":"js/404.js","publicPath":"/templates/bundle/js/404.js","path":"C:\\Users\\Gory\\pycharmprojects\\vaykae\\templates\\bundle\\js\\404.js"}],"500":[{"name":"js/500.js","publicPath":"/templates/bundle/js/500.js","path":"C:\\Users\\Gory\\pycharmprojects\\vaykae\\templates\\bundle\\js\\500.js"}],"home":[{"name":"js/home.js","publicPath":"/templates/bundle/js/home.js","path":"C:\\Users\\Gory\\pycharmprojects\\vaykae\\templates\\bundle\\js\\home.js"},{"name":"css/home.css","publicPath":"/templates/bundle/css/home.css","path":"C:\\Users\\Gory\\pycharmprojects\\vaykae\\templates\\bundle\\css\\home.css"}],"vendors":[{"name":"js/vendors.js","publicPath":"/templates/bundle/js/vendors.js","path":"C:\\Users\\Gory\\pycharmprojects\\vaykae\\templates\\bundle\\js\\vendors.js"}]}}